odoo/addons/sale_order_line_position/README.rst
odoo/addons/sale_order_line_position/__init__.py
odoo/addons/sale_order_line_position/__manifest__.py
odoo/addons/sale_order_line_position/i18n/ca.po
odoo/addons/sale_order_line_position/i18n/de.po
odoo/addons/sale_order_line_position/i18n/it.po
odoo/addons/sale_order_line_position/i18n/sale_order_line_position.pot
odoo/addons/sale_order_line_position/i18n/tr.po
odoo/addons/sale_order_line_position/models/__init__.py
odoo/addons/sale_order_line_position/models/ir_actions_report.py
odoo/addons/sale_order_line_position/models/res_company.py
odoo/addons/sale_order_line_position/models/res_config_settings.py
odoo/addons/sale_order_line_position/models/sale_order.py
odoo/addons/sale_order_line_position/models/sale_order_line.py
odoo/addons/sale_order_line_position/readme/CONTRIBUTORS.md
odoo/addons/sale_order_line_position/readme/CREDITS.md
odoo/addons/sale_order_line_position/readme/DESCRIPTION.md
odoo/addons/sale_order_line_position/readme/ROADMAP.md
odoo/addons/sale_order_line_position/report/sale_order_report.xml
odoo/addons/sale_order_line_position/static/description/icon.png
odoo/addons/sale_order_line_position/static/description/index.html
odoo/addons/sale_order_line_position/tests/__init__.py
odoo/addons/sale_order_line_position/tests/test_sale_order_line_position.py
odoo/addons/sale_order_line_position/views/res_config_settings.xml
odoo/addons/sale_order_line_position/views/sale_order.xml
odoo_addon_sale_order_line_position-18.0.1.0.1.dist-info/METADATA
odoo_addon_sale_order_line_position-18.0.1.0.1.dist-info/WHEEL
odoo_addon_sale_order_line_position-18.0.1.0.1.dist-info/top_level.txt
odoo_addon_sale_order_line_position-18.0.1.0.1.dist-info/RECORD
